FlowInput/__init__.py
FlowInput/_colors.py
FlowInput/_cursor.py
FlowInput/_input.py
FlowInput/_keyboard.py
FlowInput/_main.py
FlowInput-1.0.24.dist-info/METADATA
FlowInput-1.0.24.dist-info/WHEEL
FlowInput-1.0.24.dist-info/top_level.txt
FlowInput-1.0.24.dist-info/RECORD
