Metadata-Version: 2.1
Name: FlowInput
Version: 1.0.24
Summary: This is the simplest module for improved work with input.
Home-page: https://github.com/FunsyCode/FlowInput
Author: Funsy
Author-email: abramovicegor842@gmail.com
Project-URL: GitHub, https://github.com/FunsyCode/FlowInput
Keywords: input flowinput
Requires-Python: >=3.11
Requires-Dist: colorama>=0.4.6
